haip/__init__.py
haip/database/__init__.py
haip/database/driver.py
haip/database/pool.py
haip/database/drivers/__init__.py
haip/database/drivers/mssql.py
haip/database/drivers/mysql.py
haip/database/drivers/oracle.py
haip_database-0.1.4.dist-info/LICENSE
haip_database-0.1.4.dist-info/METADATA
haip_database-0.1.4.dist-info/WHEEL
haip_database-0.1.4.dist-info/top_level.txt
haip_database-0.1.4.dist-info/RECORD
