Metadata-Version: 2.1
Name: haip-database
Version: 0.1.4
Summary: A generic database interface.
Home-page: https://github.com/haipdev/database
Author: Reinhard Hainz
Author-email: reinhard.hainz@gmail.com
License: UNKNOWN
Platform: UNKNOWN
Classifier: Programming Language :: Python :: 3
Classifier: License :: OSI Approved :: MIT License
Classifier: Operating System :: OS Independent
Requires-Dist: asgiref
Requires-Dist: haip-config
Requires-Dist: haip-template
